nanoid/__init__.py
nanoid/algorithm.py
nanoid/generate.py
nanoid/method.py
nanoid/non_secure_generate.py
nanoid/resources.py
python_nanoid-2.0.0.dist-info/LICENSE
python_nanoid-2.0.0.dist-info/METADATA
python_nanoid-2.0.0.dist-info/WHEEL
python_nanoid-2.0.0.dist-info/top_level.txt
python_nanoid-2.0.0.dist-info/RECORD
