Metadata-Version: 2.1
Name: python-nanoid
Version: 2.0.0
Summary: A tiny, secure, URL-friendly, unique string ID generator for Python
Home-page: https://github.com/thenoobicat/python-nanoid
Author: TheNoobiCat
Author-email: 127432361+TheNoobiCat@users.noreply.github.com
License: MIT
Classifier: License :: OSI Approved :: MIT License
Classifier: Programming Language :: Python
Classifier: Operating System :: OS Independent
Classifier: Topic :: Utilities
License-File: LICENSE
